{
    "id": "ML1167",
    "mood": "sad",
    "artist": "The Decemberists",
    "title": "The Hazards of Love 4 (The Drowned)",
    "song": {
        "_type": "song",
        "annotation_count": 11,
        "api_path": "/songs/185190",
        "artist_names": "The Decemberists",
        "full_title": "The Hazards of Love 4 (The Drowned) by\u00a0The\u00a0Decemberists",
        "header_image_thumbnail_url": "https://images.genius.com/a41d1f9071c6d4205e245da86b63eceb.300x300x1.jpg",
        "header_image_url": "https://images.genius.com/a41d1f9071c6d4205e245da86b63eceb.500x500x1.jpg",
        "id": 185190,
        "instrumental": false,
        "language": "en",
        "lyrics_owner_id": 249752,
        "lyrics_state": "complete",
        "lyrics_updated_at": 1663129968,
        "path": "/The-decemberists-the-hazards-of-love-4-the-drowned-lyrics",
        "pyongs_count": null,
        "relationships_index_url": "https://genius.com/The-decemberists-the-hazards-of-love-4-the-drowned-sample",
        "release_date_components": {
            "year": 2009,
            "month": 3,
            "day": 24
        },
        "release_date_for_display": "March 24, 2009",
        "release_date_with_abbreviated_month_for_display": "Mar. 24, 2009",
        "song_art_image_thumbnail_url": "https://images.genius.com/a41d1f9071c6d4205e245da86b63eceb.300x300x1.jpg",
        "song_art_image_url": "https://images.genius.com/a41d1f9071c6d4205e245da86b63eceb.500x500x1.jpg",
        "stats": {
            "unreviewed_annotations": 6,
            "hot": false,
            "pageviews": 12358
        },
        "title": "The Hazards of Love 4 (The Drowned)",
        "title_with_featured": "The Hazards of Love 4 (The Drowned)",
        "updated_by_human_at": 1663129968,
        "url": "https://genius.com/The-decemberists-the-hazards-of-love-4-the-drowned-lyrics",
        "featured_artists": [],
        "primary_artist": {
            "_type": "artist",
            "api_path": "/artists/21125",
            "header_image_url": "https://images.genius.com/adfec600b8215bf61fb2e70ce44324fc.1000x750x1.jpg",
            "id": 21125,
            "image_url": "https://images.genius.com/11fae7f37c41d3cf265f756bddb4fa32.630x630x1.jpg",
            "index_character": "d",
            "is_meme_verified": false,
            "is_verified": false,
            "name": "The Decemberists",
            "slug": "The-decemberists",
            "url": "https://genius.com/artists/The-decemberists"
        },
        "artist": "The Decemberists",
        "lyrics": "The Hazards of Love 4 (The Drowned) Lyrics[Verse 1]\nMargaret arrayed the rocks\nAround the hull before it was sinking\nA million stones, a million bones\nA million holes within the chinking\n\n[Verse 2]\nAnd painting rings around your eyes\nThese peppered holes so filled with crying\nA whisper weighed upon the tattered down\nWhere you and I were lying\n[Verse 3]\nTell me now, tell me this\nA forest's son, a river's daughter\nA willow on the willow wisp\nOur ghosts will wander all of the water\n\n[Verse 4]\nSo let's be married here today\nThese rushing waves to bear our witness\nAnd we will lie like river stones\nRolling only where it takes us\n\n[Chorus]\nBut I pulled you and I called you here (Didn't I, didn't I, didn't I?)\nAnd I caught you and I brought you here (Didn't I, didn't I, didn't I?)\nThese hazards of love\nNever more will trouble us\n\n[Verse 5]\nOh Margaret, the lapping waves\nAre licking quietly at our ankles\nAnother bow, another breath\nThis brilliant chill's come for the shackle\n\n[Verse 6]\nWith this long last rush of air\nWe speak our vows and starry whispers\nWhen the waves came crashing down\nHe closed his eyes and softly kissed her\nYou might also like[Chorus]\nBut I pulled you and I called you here (Didn't I, didn't I, didn't I?)\nAnd I caught you and I brought you here (Didn't I, didn't I, didn't I?)\nThese hazards of love\nNever more will trouble us\n\n[Refrain]\nAnd these hazards of love\nNever more will trouble usEmbed"
    }
}