{
    "id": "ML1446",
    "mood": "relaxed",
    "artist": "Madredeus",
    "title": "O Para\u00edso",
    "song": {
        "_type": "song",
        "annotation_count": 1,
        "api_path": "/songs/1287614",
        "artist_names": "Madredeus",
        "full_title": "O Para\u00edso by\u00a0Madredeus",
        "header_image_thumbnail_url": "https://images.genius.com/54b082e092369302824e940d6ff60046.300x300x1.jpg",
        "header_image_url": "https://images.genius.com/54b082e092369302824e940d6ff60046.505x505x1.jpg",
        "id": 1287614,
        "instrumental": false,
        "language": "pt",
        "lyrics_owner_id": 1549345,
        "lyrics_state": "complete",
        "lyrics_updated_at": 1429745027,
        "path": "/Madredeus-o-paraiso-lyrics",
        "pyongs_count": null,
        "relationships_index_url": "https://genius.com/Madredeus-o-paraiso-sample",
        "release_date_components": null,
        "release_date_for_display": null,
        "release_date_with_abbreviated_month_for_display": null,
        "song_art_image_thumbnail_url": "https://images.genius.com/54b082e092369302824e940d6ff60046.300x300x1.jpg",
        "song_art_image_url": "https://images.genius.com/54b082e092369302824e940d6ff60046.505x505x1.jpg",
        "stats": {
            "unreviewed_annotations": 0,
            "hot": false
        },
        "title": "O Para\u00edso",
        "title_with_featured": "O Para\u00edso",
        "updated_by_human_at": 1477061148,
        "url": "https://genius.com/Madredeus-o-paraiso-lyrics",
        "featured_artists": [],
        "primary_artist": {
            "_type": "artist",
            "api_path": "/artists/344025",
            "header_image_url": "https://images.genius.com/6040494f268945b0fff95d2861fc3488.537x118x1.jpg",
            "id": 344025,
            "image_url": "https://images.genius.com/2a542aa1d4f797693a0d32cbc75dd6b7.533x533x1.jpg",
            "index_character": "m",
            "is_meme_verified": false,
            "is_verified": false,
            "name": "Madredeus",
            "slug": "Madredeus",
            "url": "https://genius.com/artists/Madredeus"
        },
        "artist": "Madredeus",
        "lyrics": "O Para\u00edso LyricsLetra e m\u00fasica: Pedro Ayres Magalh\u00e3es\nSubi a escada de papel\u00e3o\nImaginada\nInvoca\u00e7\u00e3o\nN\u00e3o leva a nada\nN\u00e3o leva n\u00e3o\n\u00c9 s\u00f3 uma escada de papel\u00e3o\nH\u00e1 outra entrada no Para\u00edso\nMais apertada\nMais sim senhor\nFoi inventada\nPor um an\u00e3o\nE est\u00e1 guardada\nPor um drag\u00e3o\nEu s\u00f3 conhe\u00e7o\nEsse caminho\nDo Para\u00edsoYou might also likeEmbed"
    }
}