{
    "id": "ML17",
    "mood": "happy",
    "artist": "Collie Buddz",
    "title": "Mamacita",
    "song": {
        "_type": "song",
        "annotation_count": 4,
        "api_path": "/songs/436430",
        "artist_names": "Collie Buddz",
        "full_title": "Mamacita by\u00a0Collie\u00a0Buddz",
        "header_image_thumbnail_url": "https://images.rapgenius.com/ed5fb541a7b88bafe7b4d7c3673662a0.300x304x1.jpg",
        "header_image_url": "https://images.rapgenius.com/ed5fb541a7b88bafe7b4d7c3673662a0.313x317x1.jpg",
        "id": 436430,
        "instrumental": false,
        "language": "en",
        "lyrics_owner_id": 523345,
        "lyrics_state": "complete",
        "lyrics_updated_at": 1537785614,
        "path": "/Collie-buddz-mamacita-lyrics",
        "pyongs_count": 4,
        "relationships_index_url": "https://genius.com/Collie-buddz-mamacita-sample",
        "release_date_components": {
            "year": 2007,
            "month": 7,
            "day": 3
        },
        "release_date_for_display": "July 3, 2007",
        "release_date_with_abbreviated_month_for_display": "Jul. 3, 2007",
        "song_art_image_thumbnail_url": "https://images.rapgenius.com/ed5fb541a7b88bafe7b4d7c3673662a0.300x304x1.jpg",
        "song_art_image_url": "https://images.rapgenius.com/ed5fb541a7b88bafe7b4d7c3673662a0.313x317x1.jpg",
        "stats": {
            "unreviewed_annotations": 2,
            "hot": false,
            "pageviews": 9004
        },
        "title": "Mamacita",
        "title_with_featured": "Mamacita",
        "updated_by_human_at": 1559077003,
        "url": "https://genius.com/Collie-buddz-mamacita-lyrics",
        "featured_artists": [],
        "primary_artist": {
            "_type": "artist",
            "api_path": "/artists/2086",
            "header_image_url": "https://images.genius.com/f88240a560fec8f673a855eac4fc6a79.1000x747x1.jpg",
            "id": 2086,
            "image_url": "https://images.genius.com/f88240a560fec8f673a855eac4fc6a79.1000x747x1.jpg",
            "index_character": "c",
            "is_meme_verified": false,
            "is_verified": false,
            "name": "Collie Buddz",
            "slug": "Collie-buddz",
            "url": "https://genius.com/artists/Collie-buddz"
        },
        "artist": "Collie Buddz",
        "lyrics": "Mamacita Lyrics[Verse 1]\nMan tend a next shot of tequila\nThe vibes tonight yeah, so sweet yah\nI man spot this sweet senorita\nWe a bounce to the bass and di tweeter\nShe look, muy bonita\nThe way she move remind me of Selena\n\n[Bridge]:\nShe rock so, she dip so\nShe wanna dance to reggae and calypso\nLook how the dress hug up pon her hips so\nLook how she move fast and a do it slow\nMuy bonita\nMamacita\n[Hook]:\nGal whine let me come behind yuh\nEh! Me make she feel alright\nWoulda dance all night if yuh want to\nEh! 'Till a mornin light\nLove how you feel in front a me so\nGal, let me hold you tight\n\n[Verse 2]\nLook deh, a pure death in the arena\nNumber one gal, prima ballerina\nLittle girl, how u fi come in here\nShe nuh drink, only smoke sensimilla\nShe look, muy bonita\nYou nuh see it, that a my Mona Lisa\n\n[Bridge]\n\n[Hook] (x2)\n\n[Verse 1]\n\n[Bridge]\n\n[Hook] (x2)You might also like4Embed"
    }
}