{
    "id": "ML563",
    "mood": "angry",
    "artist": "Marilyn Manson",
    "title": "Irresponsible Hate Anthem",
    "song": {
        "_type": "song",
        "annotation_count": 21,
        "api_path": "/songs/416894",
        "artist_names": "Marilyn Manson",
        "full_title": "Irresponsible Hate Anthem by\u00a0Marilyn\u00a0Manson",
        "header_image_thumbnail_url": "https://images.genius.com/fecae07d6d2325d35a952a9876e72ea1.300x300x1.jpg",
        "header_image_url": "https://images.genius.com/fecae07d6d2325d35a952a9876e72ea1.905x905x1.jpg",
        "id": 416894,
        "instrumental": false,
        "language": "en",
        "lyrics_owner_id": 186362,
        "lyrics_state": "complete",
        "lyrics_updated_at": 1653496349,
        "path": "/Marilyn-manson-irresponsible-hate-anthem-lyrics",
        "pyongs_count": 12,
        "relationships_index_url": "https://genius.com/Marilyn-manson-irresponsible-hate-anthem-sample",
        "release_date_components": {
            "year": 1996,
            "month": 10,
            "day": 8
        },
        "release_date_for_display": "October 8, 1996",
        "release_date_with_abbreviated_month_for_display": "Oct. 8, 1996",
        "song_art_image_thumbnail_url": "https://images.genius.com/fecae07d6d2325d35a952a9876e72ea1.300x300x1.jpg",
        "song_art_image_url": "https://images.genius.com/fecae07d6d2325d35a952a9876e72ea1.905x905x1.jpg",
        "stats": {
            "unreviewed_annotations": 8,
            "hot": false,
            "pageviews": 75921
        },
        "title": "Irresponsible Hate Anthem",
        "title_with_featured": "Irresponsible Hate Anthem",
        "updated_by_human_at": 1659023435,
        "url": "https://genius.com/Marilyn-manson-irresponsible-hate-anthem-lyrics",
        "featured_artists": [],
        "primary_artist": {
            "_type": "artist",
            "api_path": "/artists/2065",
            "header_image_url": "https://images.genius.com/5a0db97e404d399703cc63eb9b803415.1000x333x1.jpg",
            "id": 2065,
            "image_url": "https://images.genius.com/11eb5a9520882f2f0891cd7d4cd462d0.900x900x1.jpg",
            "index_character": "m",
            "is_meme_verified": true,
            "is_verified": true,
            "name": "Marilyn Manson",
            "slug": "Marilyn-manson",
            "url": "https://genius.com/artists/Marilyn-manson",
            "iq": 869
        },
        "artist": "Marilyn Manson",
        "lyrics": "TranslationsNederlands\u0420\u0443\u0441\u0441\u043a\u0438\u0439Irresponsible Hate Anthem Lyrics[Intro]\nWhen you are suffering, know that I have betrayed you\nAnd all the children sing\nWe hate love, we love hate\n\"We hate love, we love hate!\"\n\"We hate love, we love hate!\"\n\n[Verse 1]\nI am so all-American, I'd sell you suicide\nI am totalitarian, I've got abortions in my eyes\nI hate the hater, I'd rape the raper\nI am the animal who will not be himself\n[Refrain]\nFuck it! Fuck it! Fuck it! Fuck it!\n\n[Verse 2]\nHey victim, should I black your eyes again?\nHey victim, you were the one who put the stick in my hand\nI am the ism, my hate's a prism\nLet's just kill everyone and let your God sort them out\n\n[Refrain]\nFuck it! Fuck it! Fuck it! Fuck it!\n\n[Chorus]\nEverybody's someone else's nigg\u200ber\nI know you are, so am I\nI wasn't born with enough middle fingers\nI don't need to choose a side\n\n[Verse 3]\nI better, better, better, better not say this\nBetter, better, better, better not tell\nBetter, better, better, better not say\nBetter, better, better, better not tell\nI hate the hater, I'd rape the raper\nI am the idiot who will not be himself\nYou might also like[Refrain]\nFuck it! Fuck it! Fuck it! Fuck it!\n\n[Chorus]\nEverybody's someone else's nigg\u200ber\nI know you are, so am I\nI wasn't born with enough middle fingers\nI don't need to choose a side\n\n[Bridge]\nAmerica can not see anything\nAmerica can not see anything\nAmerica can not see anything\nHistory was written by the winner\n\n[Refrain]\nFuck it! Fuck it! Fuck it!\nFuck! Fuck! Fuck!\n\n[Chorus]\nEverybody's someone else's nigg\u200ber\nI know you are, so am I\nI wasn't born with enough middle fingers\nI don't need to choose a side12Embed"
    }
}