{
    "id": "ML574",
    "mood": "sad",
    "artist": "Diary of Dreams",
    "title": "Tears of Laughter",
    "song": {
        "_type": "song",
        "annotation_count": 18,
        "api_path": "/songs/923301",
        "artist_names": "Diary of Dreams",
        "full_title": "Tears Of Laughter by\u00a0Diary\u00a0of Dreams",
        "header_image_thumbnail_url": "https://images.genius.com/207807cf6d826dc798d56141eccbaeff.193x193x1.jpg",
        "header_image_url": "https://images.genius.com/207807cf6d826dc798d56141eccbaeff.193x193x1.jpg",
        "id": 923301,
        "instrumental": false,
        "language": "en",
        "lyrics_owner_id": 1549345,
        "lyrics_state": "complete",
        "lyrics_updated_at": 1526568231,
        "path": "/Diary-of-dreams-tears-of-laughter-lyrics",
        "pyongs_count": null,
        "relationships_index_url": "https://genius.com/Diary-of-dreams-tears-of-laughter-sample",
        "release_date_components": {
            "year": 1996,
            "month": null,
            "day": null
        },
        "release_date_for_display": "1996",
        "release_date_with_abbreviated_month_for_display": "1996",
        "song_art_image_thumbnail_url": "https://images.genius.com/207807cf6d826dc798d56141eccbaeff.193x193x1.jpg",
        "song_art_image_url": "https://images.genius.com/207807cf6d826dc798d56141eccbaeff.193x193x1.jpg",
        "stats": {
            "unreviewed_annotations": 18,
            "hot": false
        },
        "title": "Tears Of Laughter",
        "title_with_featured": "Tears Of Laughter",
        "updated_by_human_at": 1619843962,
        "url": "https://genius.com/Diary-of-dreams-tears-of-laughter-lyrics",
        "featured_artists": [],
        "primary_artist": {
            "_type": "artist",
            "api_path": "/artists/349571",
            "header_image_url": "https://images.genius.com/078a300ab48e3e6d8af7519071f20b62.600x600x1.jpg",
            "id": 349571,
            "image_url": "https://images.genius.com/078a300ab48e3e6d8af7519071f20b62.600x600x1.jpg",
            "index_character": "d",
            "is_meme_verified": false,
            "is_verified": false,
            "name": "Diary of Dreams",
            "slug": "Diary-of-dreams",
            "url": "https://genius.com/artists/Diary-of-dreams"
        },
        "artist": "Diary of Dreams",
        "lyrics": "Tears Of Laughter LyricsI would be crying tears of laughter\nIf I could see me smile again\nI still reach for the stars, but all I touch is my horizon\nI still believe my eyes, but all I see is my blindness\nI still reach for the stars, but all I touch is my horizon\nI still believe my ears, but all I hear is lasting silence\nLike a disciple of a witness\nI judge upon my sacred eye\nStill I found the origin\nIn what's left of me inside\nCan I call this my burden\nOr is this just my dream to fly?\nI would be crying tears of laughter\nIf I could see me smile again\nWeaker, weaker every day\nI forgot my urge to fly away\nAnd is my life as bare as it is?\nCold and lonely enough?\nHave you achieved what you were longing for?\nSad enough this cannot be undone\nI drop my eyes and shiver as I see\nThe reflection in the mirror of me\nHave you given up, my friend?\nForgiveness be mine\n\nI still reach for the stars, but all I touch is my horizon\nCan I call this my burden\nOr is this just my dream to fly?\nI would be crying tears of laughter\nIf I could see me smile againYou might also likeEmbed"
    }
}