{
    "id": "ML745",
    "mood": "sad",
    "artist": "Saybia",
    "title": "Guardian Angel",
    "song": {
        "_type": "song",
        "annotation_count": 1,
        "api_path": "/songs/874123",
        "artist_names": "Saybia",
        "full_title": "Guardian Angel by\u00a0Saybia",
        "header_image_thumbnail_url": "https://images.genius.com/fe669677adf00f662dfa86b4e09ca2f5.300x298x1.jpg",
        "header_image_url": "https://images.genius.com/fe669677adf00f662dfa86b4e09ca2f5.1000x992x1.jpg",
        "id": 874123,
        "instrumental": false,
        "language": "en",
        "lyrics_owner_id": 1549345,
        "lyrics_state": "complete",
        "lyrics_updated_at": 1429294612,
        "path": "/Saybia-guardian-angel-lyrics",
        "pyongs_count": null,
        "relationships_index_url": "https://genius.com/Saybia-guardian-angel-sample",
        "release_date_components": null,
        "release_date_for_display": null,
        "release_date_with_abbreviated_month_for_display": null,
        "song_art_image_thumbnail_url": "https://images.genius.com/fe669677adf00f662dfa86b4e09ca2f5.300x298x1.jpg",
        "song_art_image_url": "https://images.genius.com/fe669677adf00f662dfa86b4e09ca2f5.1000x992x1.jpg",
        "stats": {
            "unreviewed_annotations": 0,
            "hot": false
        },
        "title": "Guardian Angel",
        "title_with_featured": "Guardian Angel",
        "updated_by_human_at": 1542422139,
        "url": "https://genius.com/Saybia-guardian-angel-lyrics",
        "featured_artists": [],
        "primary_artist": {
            "_type": "artist",
            "api_path": "/artists/358295",
            "header_image_url": "https://images.genius.com/5145eb10f9a9bf0edf2dd079031a561e.620x330x1.png",
            "id": 358295,
            "image_url": "https://images.genius.com/16cfeca1153ba00dc4cf74917b3b0734.971x971x1.jpg",
            "index_character": "s",
            "is_meme_verified": false,
            "is_verified": false,
            "name": "Saybia",
            "slug": "Saybia",
            "url": "https://genius.com/artists/Saybia"
        },
        "artist": "Saybia",
        "lyrics": "Guardian Angel LyricsDo you remember?\nThe laughter and the joy\nDo you remember?\nDo you remember?\nDriving in our car\nDo you remember?\nSwimming in that lake\nJust the five of us\nAgainst the rest of the world\nGuardian angel left us bleeding\nGuardian angel left us screaming\nGuardian angel?\nDo you remember?\nFireworks by the sea\nDo you remember?\nThe exact time we went dry on gasoline\nJust the five of us\nAgainst the rest of the world\nGuardian angel left us bleeding\nGuardian angel left us screaming\nGuardian angel?\nDo you remember?You might also likeEmbed"
    }
}